nestorix/__init__.py
nestorix/nestorix.py
nestorix/nexel.py
nestorix-4.0.0.dist-info/LICENSE
nestorix-4.0.0.dist-info/METADATA
nestorix-4.0.0.dist-info/WHEEL
nestorix-4.0.0.dist-info/top_level.txt
nestorix-4.0.0.dist-info/RECORD
