Metadata-Version: 2.1
Name: nestorix
Version: 4.0.0
Summary: Nestorix: A proprietary Python toolkit for deeply nested data manipulation and analysis.
Home-page: https://github.com/yourusername/nestorix
Author: Ayush Agrawal
Author-email: aagrawal963@gmail.com
License: Proprietary
Keywords: nested-data,tree-structure,linked-list,data-structure,educational-data,data-manipulation,python-tools,dstruct,data-analysis,curriculum-parser,matrix-conversion,glaze,ayushlist,nestorix
Classifier: Development Status :: 5 - Production/Stable
Classifier: Intended Audience :: Developers
Classifier: Intended Audience :: Education
Classifier: Topic :: Software Development :: Libraries
Classifier: Topic :: Scientific/Engineering :: Information Analysis
Classifier: License :: Other/Proprietary License
Classifier: Programming Language :: Python :: 3
Classifier: Programming Language :: Python :: 3.7
Classifier: Programming Language :: Python :: 3.8
Classifier: Programming Language :: Python :: 3.9
Classifier: Programming Language :: Python :: 3.10
Requires-Python: >=3.7
License-File: LICENSE
Requires-Dist: numpy
